shareinator/__init__.py
shareinator/receiver.py
shareinator/sender.py
shareinator/shareinator.py
shareinator/GUI/__init__.py
shareinator/GUI/mainGui.py
shareinator/GUI/mainPAGE.py
shareinator/GUI/receiver.py
shareinator/GUI/receivingFile1.py
shareinator/GUI/sender.py
shareinator/GUI/sender1.py
shareinator/GUI/sender2.py
shareinator/GUI/sendingfile.py
shareinator/utils/SSHconfigure.py
shareinator/utils/__init__.py
shareinator/utils/receiverchecks.py
shareinator/utils/scanner.py
shareinator/utils/senderchecks.py
shareinator-0.0.1.dist-info/DESCRIPTION.rst
shareinator-0.0.1.dist-info/METADATA
shareinator-0.0.1.dist-info/RECORD
shareinator-0.0.1.dist-info/WHEEL
shareinator-0.0.1.dist-info/entry_points.txt
shareinator-0.0.1.dist-info/metadata.json
shareinator-0.0.1.dist-info/top_level.txt
