Metadata-Version: 2.0
Name: shareinator
Version: 0.0.1
Summary: Share files using ssh on same network
Home-page: https://github.com/GDGVIT/ssh
Author: GDGVIT
Author-email: gdgvitvellore@gmail.com
License: UNKNOWN
Platform: UNKNOWN
Classifier: Development Status :: 3 - Alpha
Classifier: License :: OSI Approved :: GNU General Public License v3 (GPLv3)
Classifier: Environment :: Console
Classifier: Environment :: X11 Applications :: Qt
Classifier: Programming Language :: Python :: 3
Classifier: Programming Language :: Python :: 3 :: Only
Classifier: Programming Language :: Python :: 3.5
Classifier: Programming Language :: Python :: Implementation :: CPython
Classifier: Topic :: Communications :: File Sharing
Requires-Python: ~=3.5
Requires-Dist: pyqt5 (>=5.6,<5.9)
